django_virtualqueryset-0.1.2.dist-info/licenses/LICENSE
virtualqueryset/__init__.py
virtualqueryset/apps.py
virtualqueryset/managers.py
virtualqueryset/models.py
virtualqueryset/queryset/__init__.py
virtualqueryset/queryset/data.py
virtualqueryset/queryset/filter.py
virtualqueryset/queryset/order.py
django_virtualqueryset-0.1.2.dist-info/METADATA
django_virtualqueryset-0.1.2.dist-info/WHEEL
django_virtualqueryset-0.1.2.dist-info/top_level.txt
django_virtualqueryset-0.1.2.dist-info/RECORD
