Metadata-Version: 2.4
Name: django-virtualqueryset
Version: 0.1.2
Summary: Django library for QuerySet-like objects not backed by a database
Author-email: Hicinformatic <hicinformatic@gmail.com>
License: MIT
Project-URL: Homepage, https://github.com/hicinformatic/django-virtualqueryset
Project-URL: Repository, https://github.com/hicinformatic/django-virtualqueryset
Project-URL: Documentation, https://github.com/hicinformatic/django-virtualqueryset#readme
Project-URL: Issues, https://github.com/hicinformatic/django-virtualqueryset/issues
Keywords: django,queryset,virtual-queryset,virtual-model,in-memory,api-queryset,json-queryset,django-orm,python
Classifier: Development Status :: 4 - Beta
Classifier: Intended Audience :: Developers
Classifier: License :: OSI Approved :: MIT License
Classifier: Framework :: Django
Classifier: Framework :: Django :: 3.2
Classifier: Framework :: Django :: 4.0
Classifier: Framework :: Django :: 4.1
Classifier: Framework :: Django :: 4.2
Classifier: Framework :: Django :: 5.0
Classifier: Programming Language :: Python :: 3
Classifier: Programming Language :: Python :: 3.10
Classifier: Programming Language :: Python :: 3.11
Classifier: Programming Language :: Python :: 3.12
Classifier: Topic :: Software Development :: Libraries :: Python Modules
Classifier: Topic :: Internet :: WWW/HTTP :: Dynamic Content
Requires-Python: >=3.10
License-File: LICENSE
Requires-Dist: Django>=3.2
Provides-Extra: dev
Requires-Dist: pytest>=8.3; extra == "dev"
Requires-Dist: pytest-django>=4.5; extra == "dev"
Requires-Dist: ruff>=0.5; extra == "dev"
Requires-Dist: mypy>=1.0; extra == "dev"
Requires-Dist: django-stubs>=5.0.0; extra == "dev"
Dynamic: license-file
